MANIFEST.in
setup.py
mad2/__init__.py
mad2/exception.py
mad2/hash.py
mad2/ipy.py
mad2/madfile.py
mad2/qdid.py
mad2/recrender.py
mad2/ui.py
mad2/util.py
mad2.egg-info/PKG-INFO
mad2.egg-info/SOURCES.txt
mad2.egg-info/dependency_links.txt
mad2.egg-info/entry_points.txt
mad2.egg-info/not-zip-safe
mad2.egg-info/pbr.json
mad2.egg-info/requires.txt
mad2.egg-info/top_level.txt
mad2/cli/__init__.py
mad2/cli/main.py
mad2/cli/msh.py
mad2/cli/qdsum.py
mad2/cli/sha1p.py
mad2/etc/filetype.config
mad2/etc/ignore.config
mad2/etc/keywords.config
mad2/etc/overlay.config
mad2/etc/plugin.config
mad2/etc/store.config
mad2/etc/plugin/report.config
mad2/etc/template/bam.config
mad2/etc/template/default.config
mad2/etc/template/vcf/find_common.config
mad2/plugin/__init__.py
mad2/plugin/backup.py
mad2/plugin/category.py
mad2/plugin/checksum.py
mad2/plugin/core.py
mad2/plugin/find.py
mad2/plugin/inotify.py
mad2/plugin/ipyscan.py
mad2/plugin/madset.py
mad2/plugin/mongo.py
mad2/plugin/onthefly.py
mad2/plugin/print.py
mad2/plugin/provenance.py
mad2/plugin/qdcheck.py
mad2/plugin/report.py
mad2/plugin/root.py
mad2/plugin/select.py
mad2/plugin/table.py
mad2/plugin/transact.py
mad2/store/__init__.py
mad2/store/mongo.py
mad2/store/sidecar.py
mad2/template/report/base.html
mad2/template/report/index.html
mad2/template/report/mad.css
mad2/template/report/singleton.html
mad2/template/report/test.html