Metadata-Version: 1.1
Name: mad2
Version: 0.3.7
Summary: create & track file metadata
Home-page: http://mfiers.github.com/mad2
Author: Mark Fiers
Author-email: mark.fiers42@gmail.com
License: UNKNOWN
Platform: UNKNOWN
Classifier: Development Status :: 4 - Beta
Classifier: Environment :: Console
Classifier: Intended Audience :: Developers
Classifier: Operating System :: OS Independent
Classifier: Programming Language :: Python
Classifier: Programming Language :: Python :: 3
Classifier: Programming Language :: Python :: 3.2
Classifier: Programming Language :: Python :: 3.3
Classifier: Programming Language :: Python :: 3.4
